{"places": [{"id": "ChIJRw0ZZ4NLW4YRLKb0Kepqb8k", "types": ["fitness_center", "yoga_studio", "gym", "sports_club", "sports_complex", "sports_activity_location", "point_of_interest", "health", "establishment"], "internationalPhoneNumber": "+1 737-727-0000", "formattedAddress": "7826 W. US Hwy 290 Suite 107, Austin, TX 78736, USA", "location": {"latitude": 30.230008499999997, "longitude": -97.88700089999999}, "rating": 4.9, "websiteUri": "https://www.hotworx.net/studio/austin-w-us-hwy-290?utm_source=GBP&utm_medium=Click", "regularOpeningHours": {"openNow": true, "periods": [{"open": {"day": 1, "hour": 11, "minute": 0}, "close": {"day": 1, "hour": 20, "minute": 0}}, {"open": {"day": 2, "hour": 11, "minute": 0}, "close": {"day": 2, "hour": 20, "minute": 0}}, {"open": {"day": 3, "hour": 11, "minute": 0}, "close": {"day": 3, "hour": 20, "minute": 0}}, {"open": {"day": 4, "hour": 11, "minute": 0}, "close": {"day": 4, "hour": 20, "minute": 0}}, {"open": {"day": 5, "hour": 9, "minute": 0}, "close": {"day": 5, "hour": 18, "minute": 0}}, {"open": {"day": 6, "hour": 11, "minute": 0}, "close": {"day": 6, "hour": 16, "minute": 0}}], "weekdayDescriptions": ["Monday: 11:00\u202fAM\u2009\u2013\u20098:00\u202fPM", "Tuesday: 11:00\u202fAM\u2009\u2013\u20098:00\u202fPM", "Wednesday: 11:00\u202fAM\u2009\u2013\u20098:00\u202fPM", "Thursday: 11:00\u202fAM\u2009\u2013\u20098:00\u202fPM", "Friday: 9:00\u202fAM\u2009\u2013\u20096:00\u202fPM", "Saturday: 11:00\u202fAM\u2009\u2013\u20094:00\u202fPM", "Sunday: Closed"], "nextCloseTime": "2026-01-21T02:00:00Z"}, "userRatingCount": 126, "displayName": {"text": "HOTWORX - Austin - Oak Hill", "languageCode": "en"}}]}